tgradish/__init__.py
tgradish/__main__.py
tgradish/config_model.py
tgradish/converter.py
tgradish/default_config.toml
tgradish/spoofer.py
tgradish-1.0.4.dist-info/LICENSE.txt
tgradish-1.0.4.dist-info/METADATA
tgradish-1.0.4.dist-info/WHEEL
tgradish-1.0.4.dist-info/entry_points.txt
tgradish-1.0.4.dist-info/top_level.txt
tgradish-1.0.4.dist-info/RECORD
