Metadata-Version: 2.1
Name: tgradish
Version: 1.0.4
Summary: Simple video converting cli utility specializing in Telegram videostickers with the ability to bypass the 3 second limit
Author-email: sliva0 <sliva0mk@gmail.com>
License: MIT License
Project-URL: Homepage, https://github.com/sliva0/tgradish
Project-URL: Author's telegram, https://t.me/sliva0
Classifier: Programming Language :: Python :: 3
Classifier: License :: OSI Approved :: MIT License
Classifier: Operating System :: OS Independent
Requires-Python: >=3.10
License-File: LICENSE.txt
Requires-Dist: pydantic ~=2.2.0
Requires-Dist: tomli ~=2.0.1
